 [
   {
     "id" : 17,
     "fName" : "Joey",
     "lName" : "Tribbiani",
     "npi" : "39318541",
     "email" : "joey@gmail.com",
     "appointment" : {
        "id" : "15",
        "date" : "06/11/2022",
        "time" : "10:00:00"
      },
     "account" : {
        "id" : 15,
        "balance" : "2000",
        "cbu" : "11111",
        "card" : [
          {
            "id" : 15,
            "number" : "15151515"
          }
        ],
        "credit" : [
          {
            "id" : 15,
            "money" : "3000"
          }
        ],
        "debt" : [
          {
            "id" : 15,
            "money" : "2000"
          }
        ],
        "discount" : [
          {
            "id" : 15,
            "percentage" : "20"
            }
        ],
        "payment" : [
          {
            "id" : 15,
            "money" : "2000"
          }
        ]
     }
   }
 ]